ludovico/__init__.py
ludovico/ludovico.py
ludovico-0.0.6.dist-info/LICENSE
ludovico-0.0.6.dist-info/METADATA
ludovico-0.0.6.dist-info/WHEEL
ludovico-0.0.6.dist-info/top_level.txt
ludovico-0.0.6.dist-info/RECORD
