Metadata-Version: 2.1
Name: ludovico
Version: 0.0.6
Summary: An opinionated DataFrame-to-TeX table generator.
Home-page: https://github.com/aitorres/ludovico
Author: Andrés Ignacio Torres
Author-email: dev@aitorres.com
License: MIT
Project-URL: Bug Tracker, https://github.com/aitorres/ludovico/issues
Platform: UNKNOWN
Classifier: Development Status :: 3 - Alpha
Classifier: Intended Audience :: Science/Research
Classifier: License :: OSI Approved :: MIT License
Classifier: Operating System :: OS Independent
Classifier: Programming Language :: Python :: 3
Classifier: Programming Language :: Python :: 3.7
Classifier: Programming Language :: Python :: 3.8
Classifier: Programming Language :: Python :: 3.9
Classifier: Programming Language :: Python :: 3.10
Classifier: Topic :: Text Processing :: Markup :: LaTeX
Requires-Python: >=3.7
License-File: LICENSE
Requires-Dist: pandas
Provides-Extra: dev
Requires-Dist: pytest ; extra == 'dev'
